tripay/__init__.py
tripay/client.py
tripay/constants.py
tripay/payment/__init__.py
tripay/payment/closed.py
tripay/payment/open.py
tripay-0.1.1.dist-info/WHEEL
tripay-0.1.1.dist-info/METADATA
tripay-0.1.1.dist-info/RECORD
