Metadata-Version: 2.1
Name: tripay
Version: 0.1.1
Summary: Tripay Client For Python (UNOFFICIAL)
Home-page: https://github.com/aprilahijriyan/tripay-python
License: MIT
Keywords: tripay,payment gateway
Author: aprilahijriyan
Author-email: 37798612+aprilahijriyan@users.noreply.github.com
Requires-Python: >=3.8,<4.0
Classifier: Development Status :: 4 - Beta
Classifier: Intended Audience :: Developers
Classifier: License :: OSI Approved :: MIT License
Classifier: Operating System :: OS Independent
Classifier: Programming Language :: Python
Classifier: Programming Language :: Python :: 3
Classifier: Programming Language :: Python :: 3.8
Classifier: Programming Language :: Python :: 3.9
Classifier: Topic :: Utilities
Requires-Dist: requests (>=2.26.0,<3.0.0)
Project-URL: Repository, https://github.com/aprilahijriyan/tripay-python
